deviceidentifier
