Metadata-Version: 1.1
Name: deviceidentifier
Version: 0.0.4
Summary: Utils to manipulate and learn from assorted device identifier formats via Reincubate's DeviceIdentifier API.
Home-page: https://github.com/reincubate/deviceidentifier-py
Author: Reincubate
Author-email: enterprise@reincubate.com
License: Proprietary
Platform: UNKNOWN
Classifier: Development Status :: 5 - Production/Stable
Classifier: Environment :: Console
Classifier: Intended Audience :: Developers
Classifier: License :: OSI Approved :: GNU General Public License (GPL)
Classifier: Natural Language :: English
Classifier: Operating System :: OS Independent
Classifier: Programming Language :: Python :: 2.6
Classifier: Programming Language :: Python :: 2.7
Classifier: Topic :: Utilities
